bondzai.validation_framework-0.0.15-py3.10-nspkg.pth
bondzai/validation_framework/__init__.py
bondzai/validation_framework/connector_handler.py
bondzai/validation_framework/dataset_handler.py
bondzai/validation_framework/event_catcher.py
bondzai/validation_framework/log_handler.py
bondzai/validation_framework/result_handler.py
bondzai/validation_framework/tar_handler.py
examples/live_scenario.py
examples/scenario.py
examples/connectors/audio_connector.py
examples/connectors/Qorvo_QM35720/connector.py
examples/connectors/Qorvo_QM35720/resources/Radar/checksum.py
examples/connectors/Qorvo_QM35720/resources/Radar/demo_radar.py
examples/connectors/Qorvo_QM35720/resources/Radar/hsspi_master.py
examples/connectors/Qorvo_QM35720/resources/Radar/radar.py
examples/connectors/Qorvo_QM35720/resources/Radar/radio_config.py
examples/connectors/Qorvo_QM35720/resources/Radar/spi/cheetah_py.py
examples/connectors/Qorvo_QM35720/resources/Radar/spi/spi_Cheetah.py
examples/connectors/Qorvo_QM35720/resources/Radar/spi/spi_FTDI.py
examples/connectors/Qorvo_QM35720/resources/Radar/spi/spi_config.py
examples/connectors/Qorvo_QM35720/resources/Radar/spi/spi_log.py
bondzai.validation_framework-0.0.15.dist-info/METADATA
bondzai.validation_framework-0.0.15.dist-info/NOTICE
bondzai.validation_framework-0.0.15.dist-info/WHEEL
bondzai.validation_framework-0.0.15.dist-info/namespace_packages.txt
bondzai.validation_framework-0.0.15.dist-info/top_level.txt
bondzai.validation_framework-0.0.15.dist-info/zip-safe
bondzai.validation_framework-0.0.15.dist-info/RECORD
