Metadata-Version: 2.1
Name: bondzai.validation-framework
Version: 0.0.15
Summary: Bondzai Validation Framework
Home-page: UNKNOWN
Author: Bondzai
License: Apache License 2.0
Keywords: davinsy,bondzai,validation
Platform: UNKNOWN
Classifier: Programming Language :: Python :: 3
Classifier: License :: OSI Approved :: Apache Software License
Classifier: Operating System :: OS Independent
License-File: NOTICE
Requires-Dist: bondzai.gateway-sdk (==0.0.22)
Requires-Dist: numpy (<2.0.0,>=1.25)
Requires-Dist: PyYAML (==6.0)
Requires-Dist: texttable (==1.6.7)
Requires-Dist: typing-extensions (==4.7.1)
Provides-Extra: dev
Requires-Dist: pylint (==2.15.9) ; extra == 'dev'
